[
    {
        "id": "615a0abd47a8ff16db7689e3",
        "balance": "$3,018.61",
        "picture": "https://img-c.udemycdn.com/course/240x135/567828_67d0.jpg",
        "name": "2021 Complete Python Bootcamp From Zero to Hero in Python",
        "company": "QIMONK"
    },
    {
        "id": "615a0abd3d50ba567422fce2",
        "balance": "$2,208.70",
        "picture": "https://img-c.udemycdn.com/course/240x135/950390_270f_3.jpg",
        "name": "Machine Learning A-Z™: Hands-On Python & R In Data Science",
        "company": "Kirill Eremenko, Hadelin de Ponteves, SuperDataScience Support, Ligency Team"
    },
    {
        "id": "615a0abdb5b352aa6dfe29f6",
        "balance": "$1,461.15",
        "picture": "https://img-c.udemycdn.com/course/240x135/903744_8eb2.jpg",
        "name": "Python for Data Science and Machine Learning Bootcamp",
        "company": "JOVIOLD"
    },
    {
        "id": "615a0abde1d540adf6f62923",
        "balance": "$3,179.04",
        "picture": "https://img-c.udemycdn.com/course/240x135/629302_8a2d_2.jpg",
        "name": "Learn Python Programming Masterclass",
        "company": "CONJURICA"
    },
    {
        "id": "615a0abde6f3e2e20c551db4",
        "balance": "$1,895.42",
        "picture": "https://img-c.udemycdn.com/course/240x135/692188_9da7_21.jpg",
        "name": "The Python Mega Course: Build 10 Real World Applications",
        "company": "INJOY"
    },
    {
        "id": "615a0abdb9b9426bbc323677",
        "balance": "$2,871.66",
        "picture": "https://img-c.udemycdn.com/course/240x135/1565838_e54e_12.jpg",
        "name": "The Complete 2021 Web Development Bootcamp",
        "company": "VINCH"
    }
]